oidm_common/__init__.py
oidm_common/distribution/__init__.py
oidm_common/distribution/download.py
oidm_common/distribution/manifest.py
oidm_common/distribution/paths.py
oidm_common/duckdb/__init__.py
oidm_common/duckdb/connection.py
oidm_common/duckdb/indexes.py
oidm_common/duckdb/search.py
oidm_common/embeddings/__init__.py
oidm_common/embeddings/cache.py
oidm_common/embeddings/generation.py
oidm_common/models/__init__.py
oidm_common/models/index_code.py
oidm_common/models/web_reference.py
oidm_common/py.typed
oidm_common-0.2.0.dist-info/WHEEL
oidm_common-0.2.0.dist-info/METADATA
oidm_common-0.2.0.dist-info/RECORD
