Metadata-Version: 2.3
Name: oidm-common
Version: 0.2.0
Summary: Shared infrastructure for OIDM packages
Requires-Dist: duckdb>=1.0
Requires-Dist: pydantic>=2.0
Requires-Dist: httpx>=0.27
Requires-Dist: platformdirs>=4.0
Requires-Dist: loguru>=0.7
Requires-Dist: pooch>=1.8
Requires-Dist: asyncer==0.0.12
Requires-Dist: openai>=1.0 ; extra == 'openai'
Requires-Python: >=3.11
Provides-Extra: openai
